MANIFEST.in
setup.py
linaro_graphics_app/__init__.py
linaro_graphics_app/admin.py
linaro_graphics_app/extension.py
linaro_graphics_app/models.py
linaro_graphics_app/tests.py
linaro_graphics_app/urls.py
linaro_graphics_app/templates/linaro_graphics_app/index.html
linaro_graphics_app/templates/linaro_graphics_app/measurement_graph_snippet.html
linaro_graphics_app/templates/linaro_graphics_app/passfail_graph_snippet.html
linaro_graphics_app/templates/linaro_graphics_app/test_case_measurement.html
linaro_graphics_app/templates/linaro_graphics_app/test_case_passfail.html
linaro_graphics_app/templates/linaro_graphics_app/test_measurement.html
linaro_graphics_app/templates/linaro_graphics_app/test_passfail.html
linaro_graphics_app/templates/linaro_graphics_app/update_table_snippet.html
linaro_graphics_app/templatetags/__init__.py
linaro_graphics_app/templatetags/graphics_tags.py
linaro_graphics_app/views/__init__.py
linaro_graphics_app/views/glmark2_es2_validate_view.py
linaro_graphics_app/views/glmark2_es2_view.py
linaro_graphics_app/views/glmemperf_view.py
linaro_graphics_app/views/measurement_view.py
linaro_graphics_app/views/passfail_view.py
linaro_graphics_app/views/util.py
linaro_graphics_dashboard.egg-info/PKG-INFO
linaro_graphics_dashboard.egg-info/SOURCES.txt
linaro_graphics_dashboard.egg-info/dependency_links.txt
linaro_graphics_dashboard.egg-info/entry_points.txt
linaro_graphics_dashboard.egg-info/not-zip-safe
linaro_graphics_dashboard.egg-info/requires.txt
linaro_graphics_dashboard.egg-info/top_level.txt