Metadata-Version: 1.0
Name: linaro-graphics-dashboard
Version: 2012.7
Summary: Linaro Graphics WG application for LAVA Server
Home-page: UNKNOWN
Author: Alexandros Frantzis
Author-email: alexandros.frantzis@linaro.org
License: AGPL
Platform: UNKNOWN
